experiment/__init__.py
experiment/experiment.py
experiment/instance.py
experiment/iteration.py
experiment/method.py
experiment/util.py
experiment_ltt-0.1.3.dist-info/LICENSE
experiment_ltt-0.1.3.dist-info/METADATA
experiment_ltt-0.1.3.dist-info/WHEEL
experiment_ltt-0.1.3.dist-info/top_level.txt
experiment_ltt-0.1.3.dist-info/RECORD
