Metadata-Version: 2.1
Name: experiment-ltt
Version: 0.1.3
Summary: Experimentation toolbox
Home-page: https://github.com/ltthacker/experiment
Author: Le Tien Thanh
Author-email: 20144075@student.hust.edu.vn
License: UNKNOWN
Platform: UNKNOWN
Classifier: Programming Language :: Python :: 3
Classifier: License :: OSI Approved :: MIT License
Classifier: Operating System :: OS Independent
Requires-Python: >=3.6
